{
  "userAgentId": "mac-os-13--firefox-130-0",
  "data": {
    "clientHello": {
      "type": "ClientHello",
      "version": "0x303 (TLS 1.2)",
      "random": {
        "unixTime": "0xA08BE832",
        "randomBytes": "60A7D181FA677F074DCA7FBCEF6BE8BCC2F80F1AD33C80BE9007D81E"
      },
      "sessionId": "FA856D9FFFA677F8F259D8DF2CF67531208B732FF1E9F812E521A15FEFF6CEEC",
      "ciphers": [
        "{0x13, 0x01} TLS_AES_128_GCM_SHA256",
        "{0x13, 0x03} TLS_CHACHA20_POLY1305_SHA256",
        "{0x13, 0x02} TLS_AES_256_GCM_SHA384",
        "{0xC0, 0x2B} TLS_ECDHE_ECDSA_WITH_AES_128_GCM_SHA256",
        "{0xC0, 0x2F} TLS_ECDHE_RSA_WITH_AES_128_GCM_SHA256",
        "{0xCC, 0xA9} TLS_ECDHE_ECDSA_WITH_CHACHA20_POLY1305_SHA256",
        "{0xCC, 0xA8} TLS_ECDHE_RSA_WITH_CHACHA20_POLY1305_SHA256",
        "{0xC0, 0x2C} TLS_ECDHE_ECDSA_WITH_AES_256_GCM_SHA384",
        "{0xC0, 0x30} TLS_ECDHE_RSA_WITH_AES_256_GCM_SHA384",
        "{0xC0, 0x0A} TLS_ECDHE_ECDSA_WITH_AES_256_CBC_SHA",
        "{0xC0, 0x09} TLS_ECDHE_ECDSA_WITH_AES_128_CBC_SHA",
        "{0xC0, 0x13} TLS_ECDHE_RSA_WITH_AES_128_CBC_SHA",
        "{0xC0, 0x14} TLS_ECDHE_RSA_WITH_AES_256_CBC_SHA",
        "{0x00, 0x9C} TLS_RSA_WITH_AES_128_GCM_SHA256",
        "{0x00, 0x9D} TLS_RSA_WITH_AES_256_GCM_SHA384",
        "{0x00, 0x2F} TLS_RSA_WITH_AES_128_CBC_SHA",
        "{0x00, 0x35} TLS_RSA_WITH_AES_256_CBC_SHA"
      ],
      "compressionMethods": [
        "No Compression (0x00)"
      ],
      "extensions": [
        {
          "type": "server_name",
          "decimal": 0,
          "values": [
            "0000 - 00 1c 00 00 19 74 6c 73-2e 64 61 2d 63 6f 6c   .....tls.da-col",
            "000f - 6c 65 63 74 2e 75 6c 69-78 65 65 2e 6f 72 67   lect.ulixee.org"
          ]
        },
        {
          "type": "extended_master_secret",
          "decimal": 23,
          "values": []
        },
        {
          "type": "renegotiate",
          "decimal": 65281,
          "values": [
            "<EMPTY>"
          ]
        },
        {
          "type": "supported_groups",
          "decimal": 10,
          "values": [
            "ecdh_x25519 (29)",
            "secp256r1 (P-256) (23)",
            "secp384r1 (P-384) (24)",
            "secp521r1 (P-521) (25)",
            "ffdhe2048 (256)",
            "ffdhe3072 (257)"
          ]
        },
        {
          "type": "ec_point_formats",
          "decimal": 11,
          "values": [
            "uncompressed (0)"
          ]
        },
        {
          "type": "session_ticket",
          "decimal": 35,
          "values": []
        },
        {
          "type": "application_layer_protocol_negotiation",
          "decimal": 16,
          "values": [
            "h2",
            "http/1.1"
          ]
        },
        {
          "type": "status_request",
          "decimal": 5,
          "values": [
            "0000 - 01 00 00 00 00                                 ....."
          ]
        },
        {
          "type": "delegated_credentials",
          "decimal": 34,
          "values": [
            "0000 - 00 08 04 03 05 03 06 03-02 03                  .........."
          ]
        },
        {
          "type": "key_share",
          "decimal": 51,
          "values": [
            "NamedGroup: ecdh_x25519 (29)",
            "key_exchange:  (len=32): 76EF4AB4BEF413CF4B1063D9C35E1A9ECFF9C59165AD260D9B1408E5025EA651",
            "NamedGroup: secp256r1 (P-256) (23)",
            "key_exchange:  (len=65): 04F7C8E55F25B1C61AB5E03583329EF8BC143246153FFF1D6AFDA4D2F3C8946396A7623E58A9B8DE8B99DA32FD95360B65F74883D7BF6C4E9087509D6DFD807B83"
          ]
        },
        {
          "type": "supported_versions",
          "decimal": 43,
          "values": [
            "TLS 1.3 (772)",
            "TLS 1.2 (771)"
          ]
        },
        {
          "type": "signature_algorithms",
          "decimal": 13,
          "values": [
            "ecdsa_secp256r1_sha256 (0x0403)",
            "ecdsa_secp384r1_sha384 (0x0503)",
            "ecdsa_secp521r1_sha512 (0x0603)",
            "rsa_pss_rsae_sha256 (0x0804)",
            "rsa_pss_rsae_sha384 (0x0805)",
            "rsa_pss_rsae_sha512 (0x0806)",
            "rsa_pkcs1_sha256 (0x0401)",
            "rsa_pkcs1_sha384 (0x0501)",
            "rsa_pkcs1_sha512 (0x0601)",
            "ecdsa_sha1 (0x0203)",
            "rsa_pkcs1_sha1 (0x0201)"
          ]
        },
        {
          "type": "psk_key_exchange_modes",
          "decimal": 45,
          "values": [
            "psk_dhe_ke (1)"
          ]
        },
        {
          "type": "record_size_limit",
          "decimal": 28,
          "values": [
            "0000 - 40 01                                          @."
          ]
        },
        {
          "type": "UNKNOWN",
          "decimal": 65037,
          "values": [
            "0000 - 00 00 01 00 03 5b 00 20-dc a8 15 bd 10 26 bb   .....[. .....&.",
            "000f - e0 7e 26 5b e1 5f 4e e3-ad 45 0a f5 8b 00 bb   .~&[._N..E.....",
            "001e - 77 3b f7 5b 69 f6 21 28-54 d6 00 ef 7e 1f a4   w;.[i.!(T...~..",
            "002d - 8a 57 c9 ee 13 9a a5 53-8b 57 5f 41 1a 77 91   .W.....S.W_A.w.",
            "003c - 3f 48 36 6d 3e 09 52 7d-89 1f c3 f1 4f da 1d   ?H6m>.R}....O..",
            "004b - ba 22 6d 91 88 05 ee 70-c1 2e ce 44 0f 46 b3   .\"m....p...D.F.",
            "005a - 35 44 e0 0d ff 3a 8f 78-44 74 c6 15 a9 8c 6d   5D...:.xDt....m",
            "0069 - f0 01 41 50 4e 8b d7 f7-95 02 4d fc 3c ca ec   ..APN.....M.<..",
            "0078 - 36 36 dc 9c d0 33 31 b0-fc b4 a7 e0 64 27 e6   66...31.....d'.",
            "0087 - f4 5f 37 4d 02 6f 00 6a-fd fe 9a cf 9a 8e dd   ._7M.o.j.......",
            "0096 - 64 3d 9e 9d 96 eb bf 64-0c fe 61 7e bb 05 1a   d=.....d..a~...",
            "00a5 - db d4 e4 02 da 21 bb 5b-49 e6 9f 9d 07 8d f4   .....!.[I......",
            "00b4 - 66 d6 de c8 4e c8 49 c7-48 10 1e e4 33 0d 77   f...N.I.H...3.w",
            "00c3 - b5 ff b9 55 60 97 ff c2-6c 8d 4a 93 9f 0e ea   ...U`...l.J....",
            "00d2 - e5 29 af 10 63 3d 12 13-8b ca 0e f9 b4 db 96   .)..c=.........",
            "00e1 - a5 fd 79 2f a4 1a 8e 6f-f1 7b db aa cc bf 1b   ..y/...o.{.....",
            "00f0 - 0a 34 be 32 92 18 ef df-eb 6a 67 73 6c 8f 13   .4.2.....jgsl..",
            "00ff - 9c 90 50 63 d1 ac fa 73-e5 21 b5 aa aa b2 e9   ..Pc...s.!.....",
            "010e - e0 98 6b b7 0e 2e c1 2c-57 c5 17               ..k....,W.."
          ]
        }
      ]
    }
  }
}